test_pypi/__init__.py
test_pypi/foo.foo
test_pypi/foo.py
test.pypi_nyoeghau-0.2.5.dist-info/LICENSE
test.pypi_nyoeghau-0.2.5.dist-info/METADATA
test.pypi_nyoeghau-0.2.5.dist-info/WHEEL
test.pypi_nyoeghau-0.2.5.dist-info/entry_points.txt
test.pypi_nyoeghau-0.2.5.dist-info/top_level.txt
test.pypi_nyoeghau-0.2.5.dist-info/RECORD
