Metadata-Version: 2.1
Name: test.pypi-nyoeghau
Version: 0.2.5
Summary: Test PyPI
Author-email: Yuanhao 'Nyoeghau' Chen <nyoeghau@nyoeghau.com>
License: # MIT License        
Project-URL: Home-page, https://github.com/edward-martyr/test.pypi
Project-URL: Bug Tracker, https://github.com/edward-martyr/test.pypi/issues
Classifier: Programming Language :: Python :: 3.10
Classifier: Programming Language :: Python :: 3.11
Classifier: Development Status :: 1 - Planning
Classifier: License :: OSI Approved :: MIT License
Classifier: Operating System :: OS Independent
Requires-Python: >=3.10
License-File: LICENSE
Provides-Extra: lint
Requires-Dist: black (<23,>=22.6.0) ; extra == 'lint'
Requires-Dist: flake8 (<5,>=4.0.1) ; extra == 'lint'
Requires-Dist: isort (<6,>=5.10.1) ; extra == 'lint'
Requires-Dist: mypy (<1,>=0.971) ; extra == 'lint'
Provides-Extra: unittest
Requires-Dist: coverage[toml] ; extra == 'unittest'
